README.md
flask_micropub.py
setup.py
Flask_Micropub.egg-info/PKG-INFO
Flask_Micropub.egg-info/SOURCES.txt
Flask_Micropub.egg-info/dependency_links.txt
Flask_Micropub.egg-info/not-zip-safe
Flask_Micropub.egg-info/requires.txt
Flask_Micropub.egg-info/top_level.txt